CHANGELOG.md
LICENSE
MANIFEST.in
README.md
pyproject.toml
setup.py
django_modeltrans.egg-info/PKG-INFO
django_modeltrans.egg-info/SOURCES.txt
django_modeltrans.egg-info/dependency_links.txt
django_modeltrans.egg-info/requires.txt
django_modeltrans.egg-info/top_level.txt
modeltrans/__init__.py
modeltrans/admin.py
modeltrans/apps.py
modeltrans/conf.py
modeltrans/fields.py
modeltrans/forms.py
modeltrans/manager.py
modeltrans/migration.py
modeltrans/translator.py
modeltrans/utils.py
modeltrans/locale/de/LC_MESSAGES/django.mo
modeltrans/locale/de/LC_MESSAGES/django.po
modeltrans/locale/fr/LC_MESSAGES/django.mo
modeltrans/locale/fr/LC_MESSAGES/django.po
modeltrans/locale/nl/LC_MESSAGES/django.mo
modeltrans/locale/nl/LC_MESSAGES/django.po
modeltrans/management/__init__.py
modeltrans/management/commands/__init__.py
modeltrans/management/commands/i18n_makemigrations.py
test_migrations/__init__.py
test_migrations/clean.py
test_migrations/manage.py
test_migrations/post_migrate_tests.py
test_migrations/pre_migrate_tests.py
test_migrations/test.py
test_migrations/migrate_test/__init__.py
test_migrations/migrate_test/settings.py
test_migrations/migrate_test/urls.py
test_migrations/migrate_test/app/__init__.py
test_migrations/migrate_test/app/admin.py
test_migrations/migrate_test/app/apps.py
test_migrations/migrate_test/app/models.py
test_migrations/migrate_test/app/translation.py
test_migrations/migrate_test/app/migrations/0001_initial.py
test_migrations/migrate_test/app/migrations/0002_auto_20170516_1521.py
test_migrations/migrate_test/app/migrations/__init__.py
tests/test_admin.py
tests/test_conf.py
tests/test_forms.py
tests/test_migration.py
tests/test_models.py
tests/test_querysets.py
tests/test_translating.py
tests/test_utils.py